MANIFEST.in
setup.cfg
setup.py
lablackey/__init__.py
lablackey/apps.py
lablackey/auth.py
lablackey/contenttypes.py
lablackey/context.py
lablackey/decorators.py
lablackey/forms.py
lablackey/loader.py
lablackey/mail.py
lablackey/mdx_urlize.py
lablackey/middleware.py
lablackey/requirements.txt
lablackey/tests.py
lablackey/tloader.py
lablackey/unrest.py
lablackey/urls.py
lablackey/utils.py
lablackey/views.py
lablackey.egg-info/PKG-INFO
lablackey.egg-info/SOURCES.txt
lablackey.egg-info/dependency_links.txt
lablackey.egg-info/top_level.txt
lablackey/api/__init__.py
lablackey/api/admin.py
lablackey/api/models.py
lablackey/api/pagination.py
lablackey/api/serializers.py
lablackey/api/tests.py
lablackey/api/urls.py
lablackey/api/views.py
lablackey/blog/__init__.py
lablackey/blog/admin.py
lablackey/blog/backend.py
lablackey/blog/context.py
lablackey/blog/forms.py
lablackey/blog/models.py
lablackey/blog/urls.py
lablackey/blog/management/__init__.py
lablackey/blog/management/commands/__init__.py
lablackey/blog/management/commands/anonymize.py
lablackey/blog/management/commands/sync_test_db.py
lablackey/blog/migrations/0001_initial.py
lablackey/blog/migrations/0002_auto_20170409_2239.py
lablackey/blog/migrations/0003_auto_20170416_1707.py
lablackey/blog/migrations/0004_auto_20170701_1658.py
lablackey/blog/migrations/0005_auto_20170701_1829.py
lablackey/blog/migrations/0006_auto_20170716_1239.py
lablackey/blog/migrations/0007_post_url.py
lablackey/blog/migrations/0008_post_extra.py
lablackey/blog/migrations/0009_post__slug.py
lablackey/blog/migrations/0010_auto_20170824_0701.py
lablackey/blog/migrations/0011_auto_20170908_1427.py
lablackey/blog/migrations/__init__.py
lablackey/blog/pygments/__init__.py
lablackey/blog/pygments/styles/__init__.py
lablackey/blog/pygments/styles/github.py
lablackey/blog/pygments/styles/solarized.py
lablackey/blog/static/blog.less
lablackey/blog/static/blog_admin.js
lablackey/blog/templates/_blog_list.html
lablackey/blog/templates/_form_messages.html
lablackey/blog/templates/blog/_content.html
lablackey/blog/templates/blog/_partial-list.html
