Metadata-Version: 1.0
Name: lablackey
Version: 0.1.4
Summary: A collection of tools for django
Home-page: https://github.com/chriscauley/lablackey
Author: Chris Cauley
Author-email: chris@lablackey.com
License: GPL
Keywords: utils,django
Platform: UNKNOWN
